{"ongoing_trials": {"tuner0": "00"}, "hyperparameters": {"space": [{"class_name": "Int", "config": {"name": "num_layers", "default": null, "conditions": [], "min_value": 1, "max_value": 10, "step": 1, "sampling": "linear"}}, {"class_name": "Int", "config": {"name": "units_0", "default": null, "conditions": [], "min_value": 32, "max_value": 128, "step": 5, "sampling": "linear"}}, {"class_name": "Int", "config": {"name": "n_connections", "default": null, "conditions": [], "min_value": 1, "max_value": 3, "step": 1, "sampling": "linear"}}, {"class_name": "Choice", "config": {"name": "n_nodes", "default": 32, "conditions": [], "values": [32, 64, 128, 256], "ordered": true}}], "values": {"num_layers": 1, "units_0": 32, "n_connections": 1, "n_nodes": 32}}, "start_order": ["00"], "end_order": [], "run_times": {}, "retry_queue": [], "seed": 42, "seed_state": 46, "tried_so_far": ["b1160195e094040104eac00b99e67a09"], "id_to_hash": {"00": "b1160195e094040104eac00b99e67a09"}, "display": {"search_start": null, "trial_start": {}, "trial_number": {}}, "num_initial_points": null, "alpha": 0.0001, "beta": 2.6}